{
  "date": "2025-09-12",
  "lastUpdated": "05:02 AM, 12 September 2025",
  "Demon Slayer - Kimetsu no Yaiba - The Movie: Infinity Castle | English": {
    "shows": 4,
    "gross": 390720,
    "sold": 618,
    "totalSeats": 900,
    "venues": 4,
    "cities": 2,
    "fastfilling": 3,
    "housefull": 0,
    "occupancy": 68.67,
    "details": [
      {
        "city": "Ahmedabad",
        "state": "Gujarat",
        "venues": 2,
        "shows": 2,
        "gross": 85440,
        "sold": 179,
        "totalSeats": 398,
        "fastfilling": 1,
        "housefull": 0,
        "occupancy": 44.97
      },
      {
        "city": "Bengaluru",
        "state": "Karnataka",
        "venues": 2,
        "shows": 2,
        "gross": 305280,
        "sold": 439,
        "totalSeats": 502,
        "fastfilling": 2,
        "housefull": 0,
        "occupancy": 87.45
      }
    ],
    "Chain_details": [
      {
        "chain": "PVR",
        "venues": 3,
        "shows": 3,
        "gross": 228020,
        "sold": 405,
        "totalSeats": 659,
        "fastfilling": 2,
        "housefull": 0,
        "occupancy": 61.46
      },
      {
        "chain": "Cinepolis",
        "venues": 1,
        "shows": 1,
        "gross": 162700,
        "sold": 213,
        "totalSeats": 241,
        "fastfilling": 1,
        "housefull": 0,
        "occupancy": 88.38
      }
    ]
  },
  "Demon Slayer - Kimetsu no Yaiba - The Movie: Infinity Castle | Japanese": {
    "shows": 19,
    "gross": 1386781,
    "sold": 2512,
    "totalSeats": 5043,
    "venues": 17,
    "cities": 10,
    "fastfilling": 8,
    "housefull": 1,
    "occupancy": 49.81,
    "details": [
      {
        "city": "Bengaluru",
        "state": "Karnataka",
        "venues": 3,
        "shows": 3,
        "gross": 500327,
        "sold": 733,
        "totalSeats": 880,
        "fastfilling": 2,
        "housefull": 1,
        "occupancy": 83.3
      },
      {
        "city": "Mumbai",
        "state": "Maharashtra",
        "venues": 2,
        "shows": 2,
        "gross": 121067,
        "sold": 289,
        "totalSeats": 591,
        "fastfilling": 1,
        "housefull": 0,
        "occupancy": 48.9
      },
      {
        "city": "Navi Mumbai",
        "state": "Maharashtra",
        "venues": 1,
        "shows": 2,
        "gross": 124550,
        "sold": 175,
        "totalSeats": 335,
        "fastfilling": 1,
        "housefull": 0,
        "occupancy": 52.24
      },
      {
        "city": "New Delhi",
        "state": "Delhi",
        "venues": 3,
        "shows": 3,
        "gross": 235147,
        "sold": 468,
        "totalSeats": 860,
        "fastfilling": 2,
        "housefull": 0,
        "occupancy": 54.42
      },
      {
        "city": "Pune",
        "state": "Maharashtra",
        "venues": 3,
        "shows": 3,
        "gross": 187850,
        "sold": 212,
        "totalSeats": 644,
        "fastfilling": 0,
        "housefull": 0,
        "occupancy": 32.92
      },
      {
        "city": "Thane",
        "state": "Maharashtra",
        "venues": 1,
        "shows": 2,
        "gross": 124750,
        "sold": 180,
        "totalSeats": 423,
        "fastfilling": 1,
        "housefull": 0,
        "occupancy": 42.55
      },
      {
        "city": "Hosur",
        "state": "Tamil Nadu",
        "venues": 1,
        "shows": 1,
        "gross": 7500,
        "sold": 50,
        "totalSeats": 350,
        "fastfilling": 0,
        "housefull": 0,
        "occupancy": 14.29
      },
      {
        "city": "Tuticorin",
        "state": "Tamil Nadu",
        "venues": 1,
        "shows": 1,
        "gross": 32950,
        "sold": 209,
        "totalSeats": 425,
        "fastfilling": 0,
        "housefull": 0,
        "occupancy": 49.18
      },
      {
        "city": "Ahmedabad",
        "state": "Gujarat",
        "venues": 1,
        "shows": 1,
        "gross": 45680,
        "sold": 157,
        "totalSeats": 214,
        "fastfilling": 1,
        "housefull": 0,
        "occupancy": 73.36
      },
      {
        "city": "Alappuzha",
        "state": "Kerala",
        "venues": 1,
        "shows": 1,
        "gross": 6960,
        "sold": 39,
        "totalSeats": 321,
        "fastfilling": 0,
        "housefull": 0,
        "occupancy": 12.15
      }
    ],
    "Chain_details": [
      {
        "chain": "PVR",
        "venues": 10,
        "shows": 10,
        "gross": 1008791,
        "sold": 1641,
        "totalSeats": 2693,
        "fastfilling": 5,
        "housefull": 1,
        "occupancy": 60.94
      },
      {
        "chain": "Cinepolis",
        "venues": 4,
        "shows": 6,
        "gross": 330580,
        "sold": 573,
        "totalSeats": 1254,
        "fastfilling": 3,
        "housefull": 0,
        "occupancy": 45.69
      },
      {
        "chain": "Grand Cinema",
        "venues": 1,
        "shows": 1,
        "gross": 7500,
        "sold": 50,
        "totalSeats": 350,
        "fastfilling": 0,
        "housefull": 0,
        "occupancy": 14.29
      },
      {
        "chain": "Sri Balakrishna Talkies",
        "venues": 1,
        "shows": 1,
        "gross": 32950,
        "sold": 209,
        "totalSeats": 425,
        "fastfilling": 0,
        "housefull": 0,
        "occupancy": 49.18
      },
      {
        "chain": "AEC Cinema",
        "venues": 1,
        "shows": 1,
        "gross": 6960,
        "sold": 39,
        "totalSeats": 321,
        "fastfilling": 0,
        "housefull": 0,
        "occupancy": 12.15
      }
    ]
  },
  "Mirai | Telugu": {
    "shows": 8,
    "gross": 631900,
    "sold": 3125,
    "totalSeats": 3919,
    "venues": 7,
    "cities": 5,
    "fastfilling": 6,
    "housefull": 1,
    "occupancy": 79.74,
    "details": [
      {
        "city": "Bengaluru",
        "state": "Karnataka",
        "venues": 3,
        "shows": 4,
        "gross": 418600,
        "sold": 2006,
        "totalSeats": 2168,
        "fastfilling": 3,
        "housefull": 1,
        "occupancy": 92.53
      },
      {
        "city": "Hosur",
        "state": "Tamil Nadu",
        "venues": 1,
        "shows": 1,
        "gross": 5850,
        "sold": 39,
        "totalSeats": 323,
        "fastfilling": 0,
        "housefull": 0,
        "occupancy": 12.07
      },
      {
        "city": "Proddatur",
        "state": "Andhra Pradesh",
        "venues": 1,
        "shows": 1,
        "gross": 59200,
        "sold": 296,
        "totalSeats": 496,
        "fastfilling": 1,
        "housefull": 0,
        "occupancy": 59.68
      },
      {
        "city": "Vinukonda",
        "state": "Andhra Pradesh",
        "venues": 1,
        "shows": 1,
        "gross": 35300,
        "sold": 211,
        "totalSeats": 330,
        "fastfilling": 1,
        "housefull": 0,
        "occupancy": 63.94
      },
      {
        "city": "Kadapa",
        "state": "Andhra Pradesh",
        "venues": 1,
        "shows": 1,
        "gross": 112950,
        "sold": 573,
        "totalSeats": 602,
        "fastfilling": 1,
        "housefull": 0,
        "occupancy": 95.18
      }
    ],
    "Chain_details": [
      {
        "chain": "TicketNew",
        "venues": 2,
        "shows": 2,
        "gross": 276700,
        "sold": 1352,
        "totalSeats": 1464,
        "fastfilling": 1,
        "housefull": 1,
        "occupancy": 92.35
      },
      {
        "chain": "Suresh Production",
        "venues": 1,
        "shows": 2,
        "gross": 141900,
        "sold": 654,
        "totalSeats": 704,
        "fastfilling": 2,
        "housefull": 0,
        "occupancy": 92.9
      },
      {
        "chain": "Grand Cinema",
        "venues": 1,
        "shows": 1,
        "gross": 5850,
        "sold": 39,
        "totalSeats": 323,
        "fastfilling": 0,
        "housefull": 0,
        "occupancy": 12.07
      },
      {
        "chain": "Araveti Theatre",
        "venues": 1,
        "shows": 1,
        "gross": 59200,
        "sold": 296,
        "totalSeats": 496,
        "fastfilling": 1,
        "housefull": 0,
        "occupancy": 59.68
      },
      {
        "chain": "Aruna A/C DTS Cinema",
        "venues": 1,
        "shows": 1,
        "gross": 35300,
        "sold": 211,
        "totalSeats": 330,
        "fastfilling": 1,
        "housefull": 0,
        "occupancy": 63.94
      },
      {
        "chain": "Raja Cinemas",
        "venues": 1,
        "shows": 1,
        "gross": 112950,
        "sold": 573,
        "totalSeats": 602,
        "fastfilling": 1,
        "housefull": 0,
        "occupancy": 95.18
      }
    ]
  }
}