{
  "date": "2025-10-08",
  "lastUpdated": "01:01 AM, 08 October 2025",
  "Kantara: A Legend Chapter-1 | Hindi": {
    "shows": 2,
    "gross": 19486,
    "sold": 118,
    "totalSeats": 435,
    "venues": 2,
    "cities": 2,
    "fastfilling": 0,
    "housefull": 0,
    "occupancy": 27.13,
    "details": [
      {
        "city": "Mumbai",
        "state": "Maharashtra",
        "venues": 1,
        "shows": 1,
        "gross": 4625,
        "sold": 25,
        "totalSeats": 205,
        "fastfilling": 0,
        "housefull": 0,
        "occupancy": 12.2
      },
      {
        "city": "Pune",
        "state": "Maharashtra",
        "venues": 1,
        "shows": 1,
        "gross": 14861,
        "sold": 93,
        "totalSeats": 230,
        "fastfilling": 0,
        "housefull": 0,
        "occupancy": 40.43
      }
    ],
    "Chain_details": [
      {
        "chain": "PVR",
        "venues": 2,
        "shows": 2,
        "gross": 19486,
        "sold": 118,
        "totalSeats": 435,
        "fastfilling": 0,
        "housefull": 0,
        "occupancy": 27.13
      }
    ]
  }
}