{
  "date": "2026-05-31",
  "lastUpdated": "04:00 AM, 31 May 2026",
  "Krishnavataram Part 1: The Heart [Hridayam] | Hindi": [
    {
      "city": "Mumbai",
      "state": "Maharashtra",
      "venue": "Maxus Cinemas, Bhayandar",
      "time": "07:15 AM",
      "audi": "SCREEN 2",
      "totalSeats": 255,
      "available": 255,
      "sold": 0,
      "gross": 0,
      "occupancy": "0.00%",
      "minsLeft": 194
    }
  ],
  "Deool Band 2 | Marathi": [
    {
      "city": "Pune",
      "state": "Maharashtra",
      "venue": "INOX Royal Heritage Mall, NIBM Ext., Pune",
      "time": "07:10 AM",
      "audi": "SCREEN 3",
      "totalSeats": 268,
      "available": 257,
      "sold": 11,
      "gross": 2340,
      "occupancy": "4.10%",
      "minsLeft": 189
    }
  ],
  "1 Nenokkadine | Telugu": [
    {
      "city": "Hyderabad",
      "state": "Telangana",
      "venue": "Sushma 70MM 2K Dolby Digital, Vanasthalipuram, Hyderabad",
      "time": "07:00 AM",
      "audi": "SUSHMA 70MM 2K DOLBY DIGITAL VANASTHALIPURAM",
      "totalSeats": 1022,
      "available": 219,
      "sold": 803,
      "gross": 95910,
      "occupancy": "78.57%",
      "minsLeft": 179
    }
  ]
}